Workbook

Sheet Current Screen Template
A1: Identifier | B1: Company Name | C1: Country of Exchange | D1: ESG Score In the last 7 FY
D2: FY0 | E2: FY-1 | F2: FY-2 | G2: FY-3 | H2: FY-4 | I2: FY-5 | J2: FY-6
D3: 3 | E3: 4 | F3: 5 | G3: 6 | H3: 7 | I3: 8 | J3: 9
A4: BBDC4.SA | B4: Banco Bradesco SA | C4: Brazil | D4: 80.020666 | E4: 78.71582 | F4: 78.287742 | G4: 80.682857 | H4: 79.130292 | I4: 79.715794 | J4: 78.963626
A5: ALPA4.SA | B5: Alpargatas SA | C5: Brazil | D5: 68.403876 | E5: 63.911547 | F5: 24.287392 | G5: 15.902739 | H5: 0 | I5: 0 | J5: 0
A6: LIGT3.SA | B6: Light SA | C6: Brazil | D6: 58.902045 | E6: 67.045989 | F6: 62.840993 | G6: 58.580844 | H6: 61.973786 | I6: 63.152152 | J6: 68.257282
A7: BRKM5.SA | B7: Braskem SA | C7: Brazil | D7: 50.954448 | E7: 53.749306 | F7: 55.824727 | G7: 55.398994 | H7: 53.848717 | I7: 59.019721 | J7: 57.890234
A8: ITUB4.SA | B8: Itau Unibanco Holding SA | C8: Brazil | D8: 84.815144 | E8: 87.827648 | F8: 89.424348 | G8: 87.638328 | H8: 89.504634 | I8: 89.820081 | J8: 89.135771
A9: LEVE3.SA | B9: MAHLE Metal Leve SA | C9: Brazil | D9: 34.944956 | E9: 31.88867 | F9: 32.932458 | G9: 25.996886 | H9: 25.523087 | I9: 0 | J9: 0
A10: CMIG4.SA | B10: Energy of Minas Gerais Co | C10: Brazil | D10: 75.07793 | E10: 74.888942 | F10: 72.332879 | G10: 75.134662 | H10: 76.761129 | I10: 74.061487 | J10: 70.332571
A11: ELET6.SA | B11: Centrais Eletricas Brasileiras SA - Eletrobras | C11: Brazil | D11: 71.756169 | E11: 69.951089 | F11: 81.713065 | G11: 80.023443 | H11: 79.279765 | I11: 74.516473 | J11: 67.624051
A12: BRFS3.SA | B12: BRF SA | C12: Brazil | D12: 81.376649 | E12: 82.30215 | F12: 81.664039 | G12: 78.244562 | H12: 77.482697 | I12: 73.206153 | J12: 74.215601
A13: VALE3.SA | B13: Vale SA | C13: Brazil | D13: 88.956899 | E13: 89.450592 | F13: 89.842715 | G13: 90.367998 | H13: 86.228756 | I13: 82.419393 | J13: 80.585822
A14: PETR4.SA | B14: Petroleo Brasileiro SA Petrobras | C14: Brazil | D14: 72.641536 | E14: 75.391845 | F14: 75.315699 | G14: 74.370008 | H14: 73.3739 | I14: 74.564112 | J14: 75.603566
A15: UNIP6.SA | B15: Unipar Carbocloro SA | C15: Brazil | D15: 17.351787 | E15: 23.365131 | F15: 0 | G15: 0 | H15: 0 | I15: 0 | J15: 0
... A2173: BOGr.AT | B2173: Bank of Greece | C2173: Greece | D2173: 2.9209793 | E2173: 2.9828889 | F2173: 2.5721528 | G2173: 2.6215482 | H2173: 1.6137423 | I2173: 1.7778911 | J2173: 2.31609

Sheet Data processed
A1: No | B1: Identifier | C1: Company Name | D1: Country of exchange | E1: ESG Score | F1: Formula | G1: Value
A2: 1 | B2: BBDC4.SA | C2: Banco Bradesco SA | D2: Brazil | E2: FY0 | F2: =VLOOKUP(C2,'Current Screen Template'!$B:$J,3,FALSE) -> 80.020666 | G2: 80.02
A3: 1 | B3: BBDC4.SA | C3: Banco Bradesco SA | D3: Brazil | E3: FY-1 | F3: =VLOOKUP(C3,'Current Screen Template'!$B:$J,4,FALSE) -> 78.71582 | G3: 78.72
A4: 1 | B4: BBDC4.SA | C4: Banco Bradesco SA | D4: Brazil | E4: FY-2 | F4: =VLOOKUP(C4,'Current Screen Template'!$B:$J,5,FALSE) -> 78.287742 | G4: 78.29
A5: 1 | B5: BBDC4.SA | C5: Banco Bradesco SA | D5: Brazil | E5: FY-3 | F5: =VLOOKUP(C5,'Current Screen Template'!$B:$J,6,FALSE) -> 80.682857 | G5: 80.68
A6: 1 | B6: BBDC4.SA | C6: Banco Bradesco SA | D6: Brazil | E6: FY-4 | F6: =VLOOKUP(C6,'Current Screen Template'!$B:$J,7,FALSE) -> 79.130292 | G6: 79.13
A7: 1 | B7: BBDC4.SA | C7: Banco Bradesco SA | D7: Brazil | E7: FY-5 | F7: =VLOOKUP(C7,'Current Screen Template'!$B:$J,8,FALSE) -> 79.715794 | G7: 79.72
A8: 1 | B8: BBDC4.SA | C8: Banco Bradesco SA | D8: Brazil | E8: FY-6 | F8: =VLOOKUP(C8,'Current Screen Template'!$B:$J,9,FALSE) -> 78.963626 | G8: 78.96
A9: 2 | B9: ALPA4.SA | C9: Alpargatas SA | D9: Brazil | E9: FY0 | F9: =VLOOKUP(C9,'Current Screen Template'!$B:$J,3,FALSE) -> 68.403876 | G9: 68.4
A10: 2 | B10: ALPA4.SA | C10: Alpargatas SA | D10: Brazil | E10: FY-1 | F10: =VLOOKUP(C10,'Current Screen Template'!$B:$J,4,FALSE) -> 63.911547 | G10: 63.91
A11: 2 | B11: ALPA4.SA | C11: Alpargatas SA | D11: Brazil | E11: FY-2 | F11: =VLOOKUP(C11,'Current Screen Template'!$B:$J,5,FALSE) -> 24.287392 | G11: 24.29
A12: 2 | B12: ALPA4.SA | C12: Alpargatas SA | D12: Brazil | E12: FY-3 | F12: =VLOOKUP(C12,'Current Screen Template'!$B:$J,6,FALSE) -> 15.902739 | G12: 15.9
A13: 2 | B13: ALPA4.SA | C13: Alpargatas SA | D13: Brazil | E13: FY-4 | F13: =VLOOKUP(C9,'Current Screen Template'!$B:$J,7,FALSE) -> 0 | G13: 0
A14: 2 | B14: ALPA4.SA | C14: Alpargatas SA | D14: Brazil | E14: FY-5 | F14: =VLOOKUP(C14,'Current Screen Template'!$B:$J,8,FALSE) -> 0 | G14: 0
A15: 2 | B15: ALPA4.SA | C15: Alpargatas SA | D15: Brazil | E15: FY-6 | F15: =VLOOKUP(C15,'Current Screen Template'!$B:$J,9,FALSE) -> 0 | G15: 0
A16: 3 | B16: LIGT3.SA | C16: Light SA | D16: Brazil | E16: FY0 | F16: =VLOOKUP(C16,'Current Screen Template'!$B:$J,3,FALSE) -> 58.902045 | G16: 58.9
A17: 3 | B17: LIGT3.SA | C17: Light SA | D17: Brazil | E17: FY-1 | F17: =VLOOKUP(C17,'Current Screen Template'!$B:$J,4,FALSE) -> 67.045989 | G17: 67.05
A18: 3 | B18: LIGT3.SA | C18: Light SA | D18: Brazil | E18: FY-2 | F18: =VLOOKUP(C18,'Current Screen Template'!$B:$J,5,FALSE) -> 62.840993 | G18: 62.84
A19: 3 | B19: LIGT3.SA | C19: Light SA | D19: Brazil | E19: FY-3 | F19: =VLOOKUP(C19,'Current Screen Template'!$B:$J,6,FALSE) -> 58.580844 | G19: 58.58
A20: 3 | B20: LIGT3.SA | C20: Light SA | D20: Brazil | E20: FY-4 | F20: =VLOOKUP(C16,'Current Screen Template'!$B:$J,7,FALSE) -> 61.973786 | G20: 61.97
A21: 3 | B21: LIGT3.SA | C21: Light SA | D21: Brazil | E21: FY-5 | F21: =VLOOKUP(C21,'Current Screen Template'!$B:$J,8,FALSE) -> 63.152152 | G21: 63.15
A22: 3 | B22: LIGT3.SA | C22: Light SA | D22: Brazil | E22: FY-6 | F22: =VLOOKUP(C22,'Current Screen Template'!$B:$J,9,FALSE) -> 68.257282 | G22: 68.26
A23: 4 | B23: BRKM5.SA | C23: Braskem SA | D23: Brazil | E23: FY0 | F23: =VLOOKUP(C23,'Current Screen Template'!$B:$J,3,FALSE) -> 50.954448 | G23: 50.95
A24: 4 | B24: BRKM5.SA | C24: Braskem SA | D24: Brazil | E24: FY-1 | F24: =VLOOKUP(C24,'Current Screen Template'!$B:$J,4,FALSE) -> 53.749306 | G24: 53.75
A25: 4 | B25: BRKM5.SA | C25: Braskem SA | D25: Brazil | E25: FY-2 | F25: =VLOOKUP(C25,'Current Screen Template'!$B:$J,5,FALSE) -> 55.824727 | G25: 55.82
A26: 4 | B26: BRKM5.SA | C26: Braskem SA | D26: Brazil | E26: FY-3 | F26: =VLOOKUP(C26,'Current Screen Template'!$B:$J,6,FALSE) -> 55.398994 | G26: 55.4
A27: 4 | B27: BRKM5.SA | C27: Braskem SA | D27: Brazil | E27: FY-4 | F27: =VLOOKUP(C23,'Current Screen Template'!$B:$J,7,FALSE) -> 53.848717 | G27: 53.85
A28: 4 | B28: BRKM5.SA | C28: Braskem SA | D28: Brazil | E28: FY-5 | F28: =VLOOKUP(C28,'Current Screen Template'!$B:$J,8,FALSE) -> 59.019721 | G28: 59.02
A29: 4 | B29: BRKM5.SA | C29: Braskem SA | D29: Brazil | E29: FY-6 | F29: =VLOOKUP(C29,'Current Screen Template'!$B:$J,9,FALSE) -> 57.890234 | G29: 57.89
A30: 5 | B30: ITUB4.SA | C30: Itau Unibanco Holding SA | D30: Brazil | E30: FY0 | F30: =VLOOKUP(C30,'Current Screen Template'!$B:$J,3,FALSE) -> 84.815144 | G30: 84.82
A31: 5 | B31: ITUB4.SA | C31: Itau Unibanco Holding SA | D31: Brazil | E31: FY-1 | F31: =VLOOKUP(C31,'Current Screen Template'!$B:$J,4,FALSE) -> 87.827648 | G31: 87.83
A32: 5 | B32: ITUB4.SA | C32: Itau Unibanco Holding SA | D32: Brazil | E32: FY-2 | F32: =VLOOKUP(C32,'Current Screen Template'!$B:$J,5,FALSE) -> 89.424348 | G32: 89.42
A33: 5 | B33: ITUB4.SA | C33: Itau Unibanco Holding SA | D33: Brazil | E33: FY-3 | F33: =VLOOKUP(C33,'Current Screen Template'!$B:$J,6,FALSE) -> 87.638328 | G33: 87.64
A34: 5 | B34: ITUB4.SA | C34: Itau Unibanco Holding SA | D34: Brazil | E34: FY-4 | F34: =VLOOKUP(C30,'Current Screen Template'!$B:$J,7,FALSE) -> 89.504634 | G34: 89.5
A35: 5 | B35: ITUB4.SA | C35: Itau Unibanco Holding SA | D35: Brazil | E35: FY-5 | F35: =VLOOKUP(C35,'Current Screen Template'!$B:$J,8,FALSE) -> 89.820081 | G35: 89.82
A36: 5 | B36: ITUB4.SA | C36: Itau Unibanco Holding SA | D36: Brazil | E36: FY-6 | F36: =VLOOKUP(C36,'Current Screen Template'!$B:$J,9,FALSE) -> 89.135771 | G36: 89.14
A37: 6 | B37: LEVE3.SA | C37: MAHLE Metal Leve SA | D37: Brazil | E37: FY0 | F37: =VLOOKUP(C37,'Current Screen Template'!$B:$J,3,FALSE) -> 34.944956 | G37: 34.94
A38: 6 | B38: LEVE3.SA | C38: MAHLE Metal Leve SA | D38: Brazil | E38: FY-1 | F38: =VLOOKUP(C38,'Current Screen Template'!$B:$J,4,FALSE) -> 31.88867 | G38: 31.89
A39: 6 | B39: LEVE3.SA | C39: MAHLE Metal Leve SA | D39: Brazil | E39: FY-2 | F39: =VLOOKUP(C39,'Current Screen Template'!$B:$J,5,FALSE) -> 32.932458 | G39: 32.93
A40: 6 | B40: LEVE3.SA | C40: MAHLE Metal Leve SA | D40: Brazil | E40: FY-3 | F40: =VLOOKUP(C40,'Current Screen Template'!$B:$J,6,FALSE) -> 25.996886 | G40: 26
A41: 6 | B41: LEVE3.SA | C41: MAHLE Metal Leve SA | D41: Brazil | E41: FY-4 | F41: =VLOOKUP(C37,'Current Screen Template'!$B:$J,7,FALSE) -> 25.523087 | G41: 25.52
A42: 6 | B42: LEVE3.SA | C42: MAHLE Metal Leve SA | D42: Brazil | E42: FY-5 | F42: =VLOOKUP(C42,'Current Screen Template'!$B:$J,8,FALSE) -> 0 | G42: 0
A43: 6 | B43: LEVE3.SA | C43: MAHLE Metal Leve SA | D43: Brazil | E43: FY-6 | F43: =VLOOKUP(C43,'Current Screen Template'!$B:$J,9,FALSE) -> 0 | G43: 0
A44: 7 | B44: CMIG4.SA | C44: Energy of Minas Gerais Co | D44: Brazil | E44: FY0 | F44: =VLOOKUP(C44,'Current Screen Template'!$B:$J,3,FALSE) -> 75.07793 | G44: 75.08
A45: 7 | B45: CMIG4.SA | C45: Energy of Minas Gerais Co | D45: Brazil | E45: FY-1 | F45: =VLOOKUP(C45,'Current Screen Template'!$B:$J,4,FALSE) -> 74.888942 | G45: 74.89
A46: 7 | B46: CMIG4.SA | C46: Energy of Minas Gerais Co | D46: Brazil | E46: FY-2 | F46: =VLOOKUP(C46,'Current Screen Template'!$B:$J,5,FALSE) -> 72.332879 | G46: 72.33
A47: 7 | B47: CMIG4.SA | C47: Energy of Minas Gerais Co | D47: Brazil | E47: FY-3 | F47: =VLOOKUP(C47,'Current Screen Template'!$B:$J,6,FALSE) -> 75.134662 | G47: 75.13
A48: 7 | B48: CMIG4.SA | C48: Energy of Minas Gerais Co | D48: Brazil | E48: FY-4 | F48: =VLOOKUP(C44,'Current Screen Template'!$B:$J,7,FALSE) -> 76.761129 | G48: 76.76
A49: 7 | B49: CMIG4.SA | C49: Energy of Minas Gerais Co | D49: Brazil | E49: FY-5 | F49: =VLOOKUP(C49,'Current Screen Template'!$B:$J,8,FALSE) -> 74.061487 | G49: 74.06
A50: 7 | B50: CMIG4.SA | C50: Energy of Minas Gerais Co | D50: Brazil | E50: FY-6 | F50: =VLOOKUP(C50,'Current Screen Template'!$B:$J,9,FALSE) -> 70.332571 | G50: 70.33
A51: 8 | B51: ELET6.SA | C51: Centrais Eletricas Brasileiras SA - Eletrobras | D51: Brazil | E51: FY0 | F51: =VLOOKUP(C51,'Current Screen Template'!$B:$J,3,FALSE) -> 71.756169 | G51: 71.76
A52: 8 | B52: ELET6.SA | C52: Centrais Eletricas Brasileiras SA - Eletrobras | D52: Brazil | E52: FY-1 | F52: =VLOOKUP(C52,'Current Screen Template'!$B:$J,4,FALSE) -> 69.951089 | G52: 69.95
A53: 8 | B53: ELET6.SA | C53: Centrais Eletricas Brasileiras SA - Eletrobras | D53: Brazil | E53: FY-2 | F53: =VLOOKUP(C53,'Current Screen Template'!$B:$J,5,FALSE) -> 81.713065 | G53: 81.71
A54: 8 | B54: ELET6.SA | C54: Centrais Eletricas Brasileiras SA - Eletrobras | D54: Brazil | E54: FY-3 | F54: =VLOOKUP(C54,'Current Screen Template'!$B:$J,6,FALSE) -> 80.023443 | G54: 80.02
A55: 8 | B55: ELET6.SA | C55: Centrais Eletricas Brasileiras SA - Eletrobras | D55: Brazil | E55: FY-4 | F55: =VLOOKUP(C51,'Current Screen Template'!$B:$J,7,FALSE) -> 79.279765 | G55: 79.28
A56: 8 | B56: ELET6.SA | C56: Centrais Eletricas Brasileiras SA - Eletrobras | D56: Brazil | E56: FY-5 | F56: =VLOOKUP(C56,'Current Screen Template'!$B:$J,8,FALSE) -> 74.516473 | G56: 74.52
A57: 8 | B57: ELET6.SA | C57: Centrais Eletricas Brasileiras SA - Eletrobras | D57: Brazil | E57: FY-6 | F57: =VLOOKUP(C57,'Current Screen Template'!$B:$J,9,FALSE) -> 67.624051 | G57: 67.62
A58: 9 | B58: BRFS3.SA | C58: BRF SA | D58: Brazil | E58: FY0 | F58: =VLOOKUP(C58,'Current Screen Template'!$B:$J,3,FALSE) -> 81.376649 | G58: 81.38
A59: 9 | B59: BRFS3.SA | C59: BRF SA | D59: Brazil | E59: FY-1 | F59: =VLOOKUP(C59,'Current Screen Template'!$B:$J,4,FALSE) -> 82.30215 | G59: 82.3
A60: 9 | B60: BRFS3.SA | C60: BRF SA | D60: Brazil | E60: FY-2 | F60: =VLOOKUP(C60,'Current Screen Template'!$B:$J,5,FALSE) -> 81.664039 | G60: 81.66
A61: 9 | B61: BRFS3.SA | C61: BRF SA | D61: Brazil | E61: FY-3 | F61: =VLOOKUP(C61,'Current Screen Template'!$B:$J,6,FALSE) -> 78.244562 | G61: 78.24
A62: 9 | B62: BRFS3.SA | C62: BRF SA | D62: Brazil | E62: FY-4 | F62: =VLOOKUP(C58,'Current Screen Template'!$B:$J,7,FALSE) -> 77.482697 | G62: 77.48
A63: 9 | B63: BRFS3.SA | C63: BRF SA | D63: Brazil | E63: FY-5 | F63: =VLOOKUP(C63,'Current Screen Template'!$B:$J,8,FALSE) -> 73.206153 | G63: 73.21
A64: 9 | B64: BRFS3.SA | C64: BRF SA | D64: Brazil | E64: FY-6 | F64: =VLOOKUP(C64,'Current Screen Template'!$B:$J,9,FALSE) -> 74.215601 | G64: 74.22
A65: 10 | B65: VALE3.SA | C65: Vale SA | D65: Brazil | E65: FY0 | F65: =VLOOKUP(C65,'Current Screen Template'!$B:$J,3,FALSE) -> 88.956899 | G65: 88.96
A66: 10 | B66: VALE3.SA | C66: Vale SA | D66: Brazil | E66: FY-1 | F66: =VLOOKUP(C66,'Current Screen Template'!$B:$J,4,FALSE) -> 89.450592 | G66: 89.45
A67: 10 | B67: VALE3.SA | C67: Vale SA | D67: Brazil | E67: FY-2 | F67: =VLOOKUP(C67,'Current Screen Template'!$B:$J,5,FALSE) -> 89.842715 | G67: 89.84
A68: 10 | B68: VALE3.SA | C68: Vale SA | D68: Brazil | E68: FY-3 | F68: =VLOOKUP(C68,'Current Screen Template'!$B:$J,6,FALSE) -> 90.367998 | G68: 90.37
A69: 10 | B69: VALE3.SA | C69: Vale SA | D69: Brazil | E69: FY-4 | F69: =VLOOKUP(C65,'Current Screen Template'!$B:$J,7,FALSE) -> 86.228756 | G69: 86.23
A70: 10 | B70: VALE3.SA | C70: Vale SA | D70: Brazil | E70: FY-5 | F70: =VLOOKUP(C70,'Current Screen Template'!$B:$J,8,FALSE) -> 82.419393 | G70: 82.42
A71: 10 | B71: VALE3.SA | C71: Vale SA | D71: Brazil | E71: FY-6 | F71: =VLOOKUP(C71,'Current Screen Template'!$B:$J,9,FALSE) -> 80.585822 | G71: 80.59
A72: 11 | B72: PETR4.SA | C72: Petroleo Brasileiro SA Petrobras | D72: Brazil | E72: FY0 | F72: =VLOOKUP(C72,'Current Screen Template'!$B:$J,3,FALSE) -> 72.641536 | G72: 72.64
A73: 11 | B73: PETR4.SA | C73: Petroleo Brasileiro SA Petrobras | D73: Brazil | E73: FY-1 | F73: =VLOOKUP(C73,'Current Screen Template'!$B:$J,4,FALSE) -> 75.391845 | G73: 75.39
A74: 11 | B74: PETR4.SA | C74: Petroleo Brasileiro SA Petrobras | D74: Brazil | E74: FY-2 | F74: =VLOOKUP(C74,'Current Screen Template'!$B:$J,5,FALSE) -> 75.315699 | G74: 75.32
A75: 11 | B75: PETR4.SA | C75: Petroleo Brasileiro SA Petrobras | D75: Brazil | E75: FY-3 | F75: =VLOOKUP(C75,'Current Screen Template'!$B:$J,6,FALSE) -> 74.370008 | G75: 74.37
A76: 11 | B76: PETR4.SA | C76: Petroleo Brasileiro SA Petrobras | D76: Brazil | E76: FY-4 | F76: =VLOOKUP(C72,'Current Screen Template'!$B:$J,7,FALSE) -> 73.3739 | G76: 73.37
A77: 11 | B77: PETR4.SA | C77: Petroleo Brasileiro SA Petrobras | D77: Brazil | E77: FY-5 | F77: =VLOOKUP(C77,'Current Screen Template'!$B:$J,8,FALSE) -> 74.564112 | G77: 74.56
A78: 11 | B78: PETR4.SA | C78: Petroleo Brasileiro SA Petrobras | D78: Brazil | E78: FY-6 | F78: =VLOOKUP(C78,'Current Screen Template'!$B:$J,9,FALSE) -> 75.603566 | G78: 75.6
A79: 12 | B79: UNIP6.SA | C79: Unipar Carbocloro SA | D79: Brazil | E79: FY0 | F79: =VLOOKUP(C79,'Current Screen Template'!$B:$J,3,FALSE) -> 17.351787 | G79: 17.35
A80: 12 | B80: UNIP6.SA | C80: Unipar Carbocloro SA | D80: Brazil | E80: FY-1 | F80: =VLOOKUP(C80,'Current Screen Template'!$B:$J,4,FALSE) -> 23.365131 | G80: 23.37
A81: 12 | B81: UNIP6.SA | C81: Unipar Carbocloro SA | D81: Brazil | E81: FY-2 | F81: =VLOOKUP(C81,'Current Screen Template'!$B:$J,5,FALSE) -> 0 | G81: 0
A82: 12 | B82: UNIP6.SA | C82: Unipar Carbocloro SA | D82: Brazil | E82: FY-3 | F82: =VLOOKUP(C82,'Current Screen Template'!$B:$J,6,FALSE) -> 0 | G82: 0
A83: 12 | B83: UNIP6.SA | C83: Unipar Carbocloro SA | D83: Brazil | E83: FY-4 | F83: =VLOOKUP(C79,'Current Screen Template'!$B:$J,7,FALSE) -> 0 | G83: 0
A84: 12 | B84: UNIP6.SA | C84: Unipar Carbocloro SA | D84: Brazil | E84: FY-5 | F84: =VLOOKUP(C84,'Current Screen Template'!$B:$J,8,FALSE) -> 0 | G84: 0
A85: 12 | B85: UNIP6.SA | C85: Unipar Carbocloro SA | D85: Brazil | E85: FY-6 | F85: =VLOOKUP(C85,'Current Screen Template'!$B:$J,9,FALSE) -> 0 | G85: 0
A86: 13 | B86: ODPV3.SA | C86: Odontoprev SA | D86: Brazil | E86: FY0 | F86: =VLOOKUP(C86,'Current Screen Template'!$B:$J,3,FALSE) -> 54.825779 | G86: 54.83
A87: 13 | B87: ODPV3.SA | C87: Odontoprev SA | D87: Brazil | E87: FY-1 | F87: =VLOOKUP(C87,'Current Screen Template'!$B:$J,4,FALSE) -> 54.094626 | G87: 54.09
A88: 13 | B88: ODPV3.SA | C88: Odontoprev SA | D88: Brazil | E88: FY-2 | F88: =VLOOKUP(C88,'Current Screen Template'!$B:$J,5,FALSE) -> 52.878346 | G88: 52.88
A89: 13 | B89: ODPV3.SA | C89: Odontoprev SA | D89: Brazil | E89: FY-3 | F89: =VLOOKUP(C89,'Current Screen Template'!$B:$J,6,FALSE) -> 50.494488 | G89: 50.49
A90: 13 | B90: ODPV3.SA | C90: Odontoprev SA | D90: Brazil | E90: FY-4 | F90: =VLOOKUP(C86,'Current Screen Template'!$B:$J,7,FALSE) -> 41.983664 | G90: 41.98
A91: 13 | B91: ODPV3.SA | C91: Odontoprev SA | D91: Brazil | E91: FY-5 | F91: =VLOOKUP(C91,'Current Screen Template'!$B:$J,8,FALSE) -> 37.23797 | G91: 37.24
A92: 13 | B92: ODPV3.SA | C92: Odontoprev SA | D92: Brazil | E92: FY-6 | F92: =VLOOKUP(C92,'Current Screen Template'!$B:$J,9,FALSE) -> 35.939253 | G92: 35.94
A93: 14 | B93: NATU3.SA | C93: Natura Cosmeticos SA | D93: Brazil | E93: FY0 | F93: =VLOOKUP(C93,'Current Screen Template'!$B:$J,3,FALSE) -> 79.342675 | G93: 79.34
A94: 14 | B94: NATU3.SA | C94: Natura Cosmeticos SA | D94: Brazil | E94: FY-1 | F94: =VLOOKUP(C94,'Current Screen Template'!$B:$J,4,FALSE) -> 72.387992 | G94: 72.39
A95: 14 | B95: NATU3.SA | C95: Natura Cosmeticos SA | D95: Brazil | E95: FY-2 | F95: =VLOOKUP(C95,'Current Screen Template'!$B:$J,5,FALSE) -> 72.672425 | G95: 72.67
A96: 14 | B96: NATU3.SA | C96: Natura Cosmeticos SA | D96: Brazil | E96: FY-3 | F96: =VLOOKUP(C96,'Current Screen Template'!$B:$J,6,FALSE) -> 70.091684 | G96: 70.09
A97: 14 | B97: NATU3.SA | C97: Natura Cosmeticos SA | D97: Brazil | E97: FY-4 | F97: =VLOOKUP(C93,'Current Screen Template'!$B:$J,7,FALSE) -> 69.756778 | G97: 69.76
A98: 14 | B98: NATU3.SA | C98: Natura Cosmeticos SA | D98: Brazil | E98: FY-5 | F98: =VLOOKUP(C98,'Current Screen Template'!$B:$J,8,FALSE) -> 70.569525 | G98: 70.57
A99: 14 | B99: NATU3.SA | C99: Natura Cosmeticos SA | D99: Brazil | E99: FY-6 | F99: =VLOOKUP(C99,'Current Screen Template'!$B:$J,9,FALSE) -> 70.345241 | G99: 70.35
A100: 15 | B100: GOAU4.SA | C100: Metalurgica Gerdau SA | D100: Brazil | E100: FY0 | F100: =VLOOKUP(C100,'Current Screen Template'!$B:$J,3,FALSE) -> 79.508679 | G100: 79.51
...
